clockwerk/__init__.py
clockwerk/logger.py
clockwerk/models.py
clockwerk/monitor.py
clockwerk/reporter.py
clockwerk/scheduler.py
clockwerk/config/__init__.py
clockwerk/config/config_models.py
clockwerk/database/__init__.py
clockwerk/database/async_connection.py
clockwerk/database/schemas.py
clockwerk/utils/__init__.py
clockwerk/utils/common.py
clockwerk/utils/database_utils.py
clockwerk-0.1.2.dist-info/licenses/LICENSE
clockwerk-0.1.2.dist-info/METADATA
clockwerk-0.1.2.dist-info/WHEEL
clockwerk-0.1.2.dist-info/top_level.txt
clockwerk-0.1.2.dist-info/RECORD
