Metadata-Version: 2.4
Name: clockwerk
Version: 0.1.2
Summary: An asynchronous uptime and latency system designed to monitor API endpoints
Author-email: HysingerDev <HysingerDev@gmail.com>
License: MIT License
Project-URL: Homepage, https://github.com/MassivelyOverthinking/Clockwerk
Project-URL: Documentation, https://github.com/MassivelyOverthinking/Clockwerk#readme
Project-URL: Source, https://github.com/MassivelyOverthinking/Clockwerk
Project-URL: Issues, https://github.com/MassivelyOverthinking/Clockwerk/issues
Keywords: API,async,uptime,monitoring,python,latency,alerts,endpoints,status checker,endpoint monitor,health checks,observability,reliability
Classifier: Development Status :: 3 - Alpha
Classifier: Intended Audience :: Developers
Classifier: License :: OSI Approved :: MIT License
Classifier: Operating System :: OS Independent
Classifier: Programming Language :: Python
Classifier: Programming Language :: Python :: 3
Classifier: Programming Language :: Python :: 3.10
Classifier: Topic :: Internet
Classifier: Topic :: System :: Logging
Classifier: Topic :: System :: Networking :: Monitoring
Classifier: Topic :: Utilities
Requires-Python: >=3.8
License-File: LICENSE
Requires-Dist: aiohttp==3.12.9
Requires-Dist: aiosmtplib==4.0.1
Requires-Dist: aiohappyeyeballs==2.6.1
Requires-Dist: aiosignal==1.3.2
Requires-Dist: attrs==25.3.0
Requires-Dist: dnspython==2.7.0
Requires-Dist: email-validator==2.2.0
Requires-Dist: frozenlist==1.6.2
Requires-Dist: idna==3.10
Requires-Dist: multidict==6.4.4
Requires-Dist: packaging==25.0
Requires-Dist: propcache==0.3.1
Requires-Dist: pydantic==2.11.5
Requires-Dist: sqlalchemy==2.0.41
Requires-Dist: tenacity==9.1.2
Requires-Dist: typing-inspection==0.4.1
Requires-Dist: yarl==1.20.0
Requires-Dist: asyncpg>=0.28
Requires-Dist: aiosqlite>=0.19
Requires-Dist: mysql-connector-python>=8.0
Provides-Extra: dev
Requires-Dist: pytest==8.4.0; extra == "dev"
Requires-Dist: pytest-asyncio==1.0.0; extra == "dev"
Requires-Dist: iniconfig==2.1.0; extra == "dev"
Requires-Dist: pluggy==1.6.0; extra == "dev"
Requires-Dist: Pygments==2.19.1; extra == "dev"
Dynamic: license-file
